{
    "achievements": {},
    "blocks": {
        "block": {}
    },
    "entities": {
        "dataserializers": {},
        "entity": {
            "block_display": [
                {
                    "class": "bfg$b",
                    "display_name": "Block Display",
                    "field": "j",
                    "height": 0.0,
                    "id": 8,
                    "metadata": [
                        {
                            "class": "bfh",
                            "entity": "~abstract_entity"
                        },
                        {
                            "bitfields": [],
                            "class": "bfg",
                            "data": [
                                {
                                    "default": -1000,
                                    "field": "q",
                                    "index": 8,
                                    "serializer": "Long",
                                    "serializer_id": 2
                                },
                                {
                                    "default": 0,
                                    "field": "r",
                                    "index": 9,
                                    "serializer": "VarInt",
                                    "serializer_id": 1
                                },
                                {
                                    "default": {
                                        "x": 0,
                                        "y": 0,
                                        "z": 0
                                    },
                                    "field": "s",
                                    "index": 10,
                                    "serializer": "Vector3f",
                                    "serializer_id": 26
                                },
                                {
                                    "default": {
                                        "x": 1.0,
                                        "y": 1.0,
                                        "z": 1.0
                                    },
                                    "field": "t",
                                    "index": 11,
                                    "serializer": "Vector3f",
                                    "serializer_id": 26
                                },
                                {
                                    "default": {
                                        "w": 1,
                                        "x": 0,
                                        "y": 0,
                                        "z": 0
                                    },
                                    "field": "u",
                                    "index": 12,
                                    "serializer": "Quaternionf",
                                    "serializer_id": 27
                                },
                                {
                                    "default": {
                                        "w": 1,
                                        "x": 0,
                                        "y": 0,
                                        "z": 0
                                    },
                                    "field": "aC",
                                    "index": 13,
                                    "serializer": "Quaternionf",
                                    "serializer_id": 27
                                },
                                {
                                    "field": "aD",
                                    "index": 14,
                                    "serializer": "Byte",
                                    "serializer_id": 0
                                },
                                {
                                    "default": -1,
                                    "field": "aE",
                                    "index": 15,
                                    "serializer": "VarInt",
                                    "serializer_id": 1
                                },
                                {
                                    "default": 1.0,
                                    "field": "aF",
                                    "index": 16,
                                    "serializer": "Float",
                                    "serializer_id": 3
                                },
                                {
                                    "default": 0.0,
                                    "field": "aG",
                                    "index": 17,
                                    "serializer": "Float",
                                    "serializer_id": 3
                                },
                                {
                                    "default": 1.0,
                                    "field": "aH",
                                    "index": 18,
                                    "serializer": "Float",
                                    "serializer_id": 3
                                },
                                {
                                    "default": 0.0,
                                    "field": "aI",
                                    "index": 19,
                                    "serializer": "Float",
                                    "serializer_id": 3
                                },
                                {
                                    "default": 0.0,
                                    "field": "aJ",
                                    "index": 20,
                                    "serializer": "Float",
                                    "serializer_id": 3
                                },
                                {
                                    "default": -1,
                                    "field": "aK",
                                    "index": 21,
                                    "serializer": "VarInt",
                                    "serializer_id": 1
                                }
                            ]
                        },
                        {
                            "bitfields": [],
                            "class": "bfg$b",
                            "data": [
                                {
                                    "field": "p",
                                    "index": 22,
                                    "serializer": "BlockState",
                                    "serializer_id": 14
                                }
                            ]
                        }
                    ],
                    "name": "block_display",
                    "width": 0.0
                },
                {
                    "class": "bfg$b",
                    "display_name": "Block Display",
                    "field": "j",
                    "height": 0.0,
                    "id": 8,
                    "metadata": [
                        {
                            "class": "bfh",
                            "entity": "~abstract_entity"
                        },
                        {
                            "bitfields": [],
                            "class": "bfg",
                            "data": [
                                {
                                    "default": 0,
                                    "field": "q",
                                    "index": 8,
                                    "serializer": "VarInt",
                                    "serializer_id": 1
                                },
                                {
                                    "default": 0,
                                    "field": "r",
                                    "index": 9,
                                    "serializer": "VarInt",
                                    "serializer_id": 1
                                },
                                {
                                    "default": {
                                        "x": 0,
                                        "y": 0,
                                        "z": 0
                                    },
                                    "field": "s",
                                    "index": 10,
                                    "serializer": "Vector3f",
                                    "serializer_id": 26
                                },
                                {
                                    "default": {
                                        "x": 1.0,
                                        "y": 1.0,
                                        "z": 1.0
                                    },
                                    "field": "t",
                                    "index": 11,
                                    "serializer": "Vector3f",
                                    "serializer_id": 26
                                },
                                {
                                    "default": {
                                        "w": 1,
                                        "x": 0,
                                        "y": 0,
                                        "z": 0
                                    },
                                    "field": "u",
                                    "index": 12,
                                    "serializer": "Quaternionf",
                                    "serializer_id": 27
                                },
                                {
                                    "default": {
                                        "w": 1,
                                        "x": 0,
                                        "y": 0,
                                        "z": 0
                                    },
                                    "field": "aC",
                                    "index": 13,
                                    "serializer": "Quaternionf",
                                    "serializer_id": 27
                                },
                                {
                                    "field": "aD",
                                    "index": 14,
                                    "serializer": "Byte",
                                    "serializer_id": 0
                                },
                                {
                                    "default": -1,
                                    "field": "aE",
                                    "index": 15,
                                    "serializer": "VarInt",
                                    "serializer_id": 1
                                },
                                {
                                    "default": 1.0,
                                    "field": "aF",
                                    "index": 16,
                                    "serializer": "Float",
                                    "serializer_id": 3
                                },
                                {
                                    "default": 0.0,
                                    "field": "aG",
                                    "index": 17,
                                    "serializer": "Float",
                                    "serializer_id": 3
                                },
                                {
                                    "default": 1.0,
                                    "field": "aH",
                                    "index": 18,
                                    "serializer": "Float",
                                    "serializer_id": 3
                                },
                                {
                                    "default": 0.0,
                                    "field": "aI",
                                    "index": 19,
                                    "serializer": "Float",
                                    "serializer_id": 3
                                },
                                {
                                    "default": 0.0,
                                    "field": "aJ",
                                    "index": 20,
                                    "serializer": "Float",
                                    "serializer_id": 3
                                },
                                {
                                    "default": -1,
                                    "field": "aK",
                                    "index": 21,
                                    "serializer": "VarInt",
                                    "serializer_id": 1
                                }
                            ]
                        },
                        {
                            "bitfields": [],
                            "class": "bfg$b",
                            "data": [
                                {
                                    "field": "p",
                                    "index": 22,
                                    "serializer": "BlockState",
                                    "serializer_id": 14
                                }
                            ]
                        }
                    ],
                    "name": "block_display",
                    "width": 0.0
                }
            ],
            "item_display": [
                {
                    "class": "bfg$j",
                    "display_name": "Item Display",
                    "field": "ae",
                    "height": 0.0,
                    "id": 55,
                    "metadata": [
                        {
                            "class": "bfh",
                            "entity": "~abstract_entity"
                        },
                        {
                            "bitfields": [],
                            "class": "bfg",
                            "data": [
                                {
                                    "default": -1000,
                                    "field": "q",
                                    "index": 8,
                                    "serializer": "Long",
                                    "serializer_id": 2
                                },
                                {
                                    "default": 0,
                                    "field": "r",
                                    "index": 9,
                                    "serializer": "VarInt",
                                    "serializer_id": 1
                                },
                                {
                                    "default": {
                                        "x": 0,
                                        "y": 0,
                                        "z": 0
                                    },
                                    "field": "s",
                                    "index": 10,
                                    "serializer": "Vector3f",
                                    "serializer_id": 26
                                },
                                {
                                    "default": {
                                        "x": 1.0,
                                        "y": 1.0,
                                        "z": 1.0
                                    },
                                    "field": "t",
                                    "index": 11,
                                    "serializer": "Vector3f",
                                    "serializer_id": 26
                                },
                                {
                                    "default": {
                                        "w": 1,
                                        "x": 0,
                                        "y": 0,
                                        "z": 0
                                    },
                                    "field": "u",
                                    "index": 12,
                                    "serializer": "Quaternionf",
                                    "serializer_id": 27
                                },
                                {
                                    "default": {
                                        "w": 1,
                                        "x": 0,
                                        "y": 0,
                                        "z": 0
                                    },
                                    "field": "aC",
                                    "index": 13,
                                    "serializer": "Quaternionf",
                                    "serializer_id": 27
                                },
                                {
                                    "field": "aD",
                                    "index": 14,
                                    "serializer": "Byte",
                                    "serializer_id": 0
                                },
                                {
                                    "default": -1,
                                    "field": "aE",
                                    "index": 15,
                                    "serializer": "VarInt",
                                    "serializer_id": 1
                                },
                                {
                                    "default": 1.0,
                                    "field": "aF",
                                    "index": 16,
                                    "serializer": "Float",
                                    "serializer_id": 3
                                },
                                {
                                    "default": 0.0,
                                    "field": "aG",
                                    "index": 17,
                                    "serializer": "Float",
                                    "serializer_id": 3
                                },
                                {
                                    "default": 1.0,
                                    "field": "aH",
                                    "index": 18,
                                    "serializer": "Float",
                                    "serializer_id": 3
                                },
                                {
                                    "default": 0.0,
                                    "field": "aI",
                                    "index": 19,
                                    "serializer": "Float",
                                    "serializer_id": 3
                                },
                                {
                                    "default": 0.0,
                                    "field": "aJ",
                                    "index": 20,
                                    "serializer": "Float",
                                    "serializer_id": 3
                                },
                                {
                                    "default": -1,
                                    "field": "aK",
                                    "index": 21,
                                    "serializer": "VarInt",
                                    "serializer_id": 1
                                }
                            ]
                        },
                        {
                            "bitfields": [],
                            "class": "bfg$j",
                            "data": [
                                {
                                    "default": "Empty",
                                    "field": "q",
                                    "index": 22,
                                    "serializer": "Slot",
                                    "serializer_id": 7
                                },
                                {
                                    "field": "r",
                                    "index": 23,
                                    "serializer": "Byte",
                                    "serializer_id": 0
                                }
                            ]
                        }
                    ],
                    "name": "item_display",
                    "width": 0.0
                },
                {
                    "class": "bfg$j",
                    "display_name": "Item Display",
                    "field": "ae",
                    "height": 0.0,
                    "id": 55,
                    "metadata": [
                        {
                            "class": "bfh",
                            "entity": "~abstract_entity"
                        },
                        {
                            "bitfields": [],
                            "class": "bfg",
                            "data": [
                                {
                                    "default": 0,
                                    "field": "q",
                                    "index": 8,
                                    "serializer": "VarInt",
                                    "serializer_id": 1
                                },
                                {
                                    "default": 0,
                                    "field": "r",
                                    "index": 9,
                                    "serializer": "VarInt",
                                    "serializer_id": 1
                                },
                                {
                                    "default": {
                                        "x": 0,
                                        "y": 0,
                                        "z": 0
                                    },
                                    "field": "s",
                                    "index": 10,
                                    "serializer": "Vector3f",
                                    "serializer_id": 26
                                },
                                {
                                    "default": {
                                        "x": 1.0,
                                        "y": 1.0,
                                        "z": 1.0
                                    },
                                    "field": "t",
                                    "index": 11,
                                    "serializer": "Vector3f",
                                    "serializer_id": 26
                                },
                                {
                                    "default": {
                                        "w": 1,
                                        "x": 0,
                                        "y": 0,
                                        "z": 0
                                    },
                                    "field": "u",
                                    "index": 12,
                                    "serializer": "Quaternionf",
                                    "serializer_id": 27
                                },
                                {
                                    "default": {
                                        "w": 1,
                                        "x": 0,
                                        "y": 0,
                                        "z": 0
                                    },
                                    "field": "aC",
                                    "index": 13,
                                    "serializer": "Quaternionf",
                                    "serializer_id": 27
                                },
                                {
                                    "field": "aD",
                                    "index": 14,
                                    "serializer": "Byte",
                                    "serializer_id": 0
                                },
                                {
                                    "default": -1,
                                    "field": "aE",
                                    "index": 15,
                                    "serializer": "VarInt",
                                    "serializer_id": 1
                                },
                                {
                                    "default": 1.0,
                                    "field": "aF",
                                    "index": 16,
                                    "serializer": "Float",
                                    "serializer_id": 3
                                },
                                {
                                    "default": 0.0,
                                    "field": "aG",
                                    "index": 17,
                                    "serializer": "Float",
                                    "serializer_id": 3
                                },
                                {
                                    "default": 1.0,
                                    "field": "aH",
                                    "index": 18,
                                    "serializer": "Float",
                                    "serializer_id": 3
                                },
                                {
                                    "default": 0.0,
                                    "field": "aI",
                                    "index": 19,
                                    "serializer": "Float",
                                    "serializer_id": 3
                                },
                                {
                                    "default": 0.0,
                                    "field": "aJ",
                                    "index": 20,
                                    "serializer": "Float",
                                    "serializer_id": 3
                                },
                                {
                                    "default": -1,
                                    "field": "aK",
                                    "index": 21,
                                    "serializer": "VarInt",
                                    "serializer_id": 1
                                }
                            ]
                        },
                        {
                            "bitfields": [],
                            "class": "bfg$j",
                            "data": [
                                {
                                    "default": "Empty",
                                    "field": "q",
                                    "index": 22,
                                    "serializer": "Slot",
                                    "serializer_id": 7
                                },
                                {
                                    "field": "r",
                                    "index": 23,
                                    "serializer": "Byte",
                                    "serializer_id": 0
                                }
                            ]
                        }
                    ],
                    "name": "item_display",
                    "width": 0.0
                }
            ],
            "text_display": [
                {
                    "class": "bfg$k",
                    "display_name": "Text Display",
                    "field": "aX",
                    "height": 0.0,
                    "id": 100,
                    "metadata": [
                        {
                            "class": "bfh",
                            "entity": "~abstract_entity"
                        },
                        {
                            "bitfields": [],
                            "class": "bfg",
                            "data": [
                                {
                                    "default": -1000,
                                    "field": "q",
                                    "index": 8,
                                    "serializer": "Long",
                                    "serializer_id": 2
                                },
                                {
                                    "default": 0,
                                    "field": "r",
                                    "index": 9,
                                    "serializer": "VarInt",
                                    "serializer_id": 1
                                },
                                {
                                    "default": {
                                        "x": 0,
                                        "y": 0,
                                        "z": 0
                                    },
                                    "field": "s",
                                    "index": 10,
                                    "serializer": "Vector3f",
                                    "serializer_id": 26
                                },
                                {
                                    "default": {
                                        "x": 1.0,
                                        "y": 1.0,
                                        "z": 1.0
                                    },
                                    "field": "t",
                                    "index": 11,
                                    "serializer": "Vector3f",
                                    "serializer_id": 26
                                },
                                {
                                    "default": {
                                        "w": 1,
                                        "x": 0,
                                        "y": 0,
                                        "z": 0
                                    },
                                    "field": "u",
                                    "index": 12,
                                    "serializer": "Quaternionf",
                                    "serializer_id": 27
                                },
                                {
                                    "default": {
                                        "w": 1,
                                        "x": 0,
                                        "y": 0,
                                        "z": 0
                                    },
                                    "field": "aC",
                                    "index": 13,
                                    "serializer": "Quaternionf",
                                    "serializer_id": 27
                                },
                                {
                                    "field": "aD",
                                    "index": 14,
                                    "serializer": "Byte",
                                    "serializer_id": 0
                                },
                                {
                                    "default": -1,
                                    "field": "aE",
                                    "index": 15,
                                    "serializer": "VarInt",
                                    "serializer_id": 1
                                },
                                {
                                    "default": 1.0,
                                    "field": "aF",
                                    "index": 16,
                                    "serializer": "Float",
                                    "serializer_id": 3
                                },
                                {
                                    "default": 0.0,
                                    "field": "aG",
                                    "index": 17,
                                    "serializer": "Float",
                                    "serializer_id": 3
                                },
                                {
                                    "default": 1.0,
                                    "field": "aH",
                                    "index": 18,
                                    "serializer": "Float",
                                    "serializer_id": 3
                                },
                                {
                                    "default": 0.0,
                                    "field": "aI",
                                    "index": 19,
                                    "serializer": "Float",
                                    "serializer_id": 3
                                },
                                {
                                    "default": 0.0,
                                    "field": "aJ",
                                    "index": 20,
                                    "serializer": "Float",
                                    "serializer_id": 3
                                },
                                {
                                    "default": -1,
                                    "field": "aK",
                                    "index": 21,
                                    "serializer": "VarInt",
                                    "serializer_id": 1
                                }
                            ]
                        },
                        {
                            "bitfields": [],
                            "class": "bfg$k",
                            "data": [
                                {
                                    "field": "aK",
                                    "index": 22,
                                    "serializer": "Chat",
                                    "serializer_id": 5
                                },
                                {
                                    "default": 200,
                                    "field": "aL",
                                    "index": 23,
                                    "serializer": "VarInt",
                                    "serializer_id": 1
                                },
                                {
                                    "default": 1073741824,
                                    "field": "aM",
                                    "index": 24,
                                    "serializer": "VarInt",
                                    "serializer_id": 1
                                },
                                {
                                    "default": -1,
                                    "field": "aN",
                                    "index": 25,
                                    "serializer": "Byte",
                                    "serializer_id": 0
                                },
                                {
                                    "default": 0,
                                    "field": "aO",
                                    "index": 26,
                                    "serializer": "Byte",
                                    "serializer_id": 0
                                }
                            ]
                        }
                    ],
                    "name": "text_display",
                    "width": 0.0
                },
                {
                    "class": "bfg$k",
                    "display_name": "Text Display",
                    "field": "aX",
                    "height": 0.0,
                    "id": 100,
                    "metadata": [
                        {
                            "class": "bfh",
                            "entity": "~abstract_entity"
                        },
                        {
                            "bitfields": [],
                            "class": "bfg",
                            "data": [
                                {
                                    "default": 0,
                                    "field": "q",
                                    "index": 8,
                                    "serializer": "VarInt",
                                    "serializer_id": 1
                                },
                                {
                                    "default": 0,
                                    "field": "r",
                                    "index": 9,
                                    "serializer": "VarInt",
                                    "serializer_id": 1
                                },
                                {
                                    "default": {
                                        "x": 0,
                                        "y": 0,
                                        "z": 0
                                    },
                                    "field": "s",
                                    "index": 10,
                                    "serializer": "Vector3f",
                                    "serializer_id": 26
                                },
                                {
                                    "default": {
                                        "x": 1.0,
                                        "y": 1.0,
                                        "z": 1.0
                                    },
                                    "field": "t",
                                    "index": 11,
                                    "serializer": "Vector3f",
                                    "serializer_id": 26
                                },
                                {
                                    "default": {
                                        "w": 1,
                                        "x": 0,
                                        "y": 0,
                                        "z": 0
                                    },
                                    "field": "u",
                                    "index": 12,
                                    "serializer": "Quaternionf",
                                    "serializer_id": 27
                                },
                                {
                                    "default": {
                                        "w": 1,
                                        "x": 0,
                                        "y": 0,
                                        "z": 0
                                    },
                                    "field": "aC",
                                    "index": 13,
                                    "serializer": "Quaternionf",
                                    "serializer_id": 27
                                },
                                {
                                    "field": "aD",
                                    "index": 14,
                                    "serializer": "Byte",
                                    "serializer_id": 0
                                },
                                {
                                    "default": -1,
                                    "field": "aE",
                                    "index": 15,
                                    "serializer": "VarInt",
                                    "serializer_id": 1
                                },
                                {
                                    "default": 1.0,
                                    "field": "aF",
                                    "index": 16,
                                    "serializer": "Float",
                                    "serializer_id": 3
                                },
                                {
                                    "default": 0.0,
                                    "field": "aG",
                                    "index": 17,
                                    "serializer": "Float",
                                    "serializer_id": 3
                                },
                                {
                                    "default": 1.0,
                                    "field": "aH",
                                    "index": 18,
                                    "serializer": "Float",
                                    "serializer_id": 3
                                },
                                {
                                    "default": 0.0,
                                    "field": "aI",
                                    "index": 19,
                                    "serializer": "Float",
                                    "serializer_id": 3
                                },
                                {
                                    "default": 0.0,
                                    "field": "aJ",
                                    "index": 20,
                                    "serializer": "Float",
                                    "serializer_id": 3
                                },
                                {
                                    "default": -1,
                                    "field": "aK",
                                    "index": 21,
                                    "serializer": "VarInt",
                                    "serializer_id": 1
                                }
                            ]
                        },
                        {
                            "bitfields": [],
                            "class": "bfg$k",
                            "data": [
                                {
                                    "field": "aK",
                                    "index": 22,
                                    "serializer": "Chat",
                                    "serializer_id": 5
                                },
                                {
                                    "default": 200,
                                    "field": "aL",
                                    "index": 23,
                                    "serializer": "VarInt",
                                    "serializer_id": 1
                                },
                                {
                                    "default": 1073741824,
                                    "field": "aM",
                                    "index": 24,
                                    "serializer": "VarInt",
                                    "serializer_id": 1
                                },
                                {
                                    "default": -1,
                                    "field": "aN",
                                    "index": 25,
                                    "serializer": "Byte",
                                    "serializer_id": 0
                                },
                                {
                                    "default": 0,
                                    "field": "aO",
                                    "index": 26,
                                    "serializer": "Byte",
                                    "serializer_id": 0
                                }
                            ]
                        }
                    ],
                    "name": "text_display",
                    "width": 0.0
                }
            ]
        }
    },
    "items": {
        "item": {}
    },
    "language": {},
    "packets": {
        "packet": {}
    },
    "pluginchannels": {},
    "recipes": {},
    "sounds": {},
    "stats": {},
    "tags": {},
    "tileentity": {
        "tileentities": {}
    },
    "version": {
        "data": [
            3333,
            3334
        ],
        "id": [
            "1.19.4-pre4",
            "1.19.4-rc1"
        ],
        "name": [
            "1.19.4 Pre-release 4",
            "1.19.4 Release Candidate 1"
        ],
        "protocol": [
            1073741947,
            1073741948
        ]
    }
}