{
    "achievements": {},
    "biomes": {
        "biome": {}
    },
    "blocks": {
        "block": {}
    },
    "entities": {
        "dataserializers": {},
        "entity": {}
    },
    "items": {
        "item": {}
    },
    "language": {
        "resourcePack": {
            "load_fail": [
                null,
                "Resource reload failed"
            ]
        }
    },
    "packets": {
        "packet": {}
    },
    "recipes": {},
    "sounds": {},
    "stats": {},
    "tags": {},
    "tileentity": {
        "tileentities": {}
    },
    "version": {
        "data": [
            2221,
            2222
        ],
        "id": [
            "1.15-pre4",
            "1.15-pre5"
        ],
        "name": [
            "1.15 Pre-release 4",
            "1.15 Pre-release 5"
        ],
        "protocol": [
            569,
            570
        ]
    }
}