{
    "achievements": {},
    "blocks": {
        "block": {}
    },
    "entities": {
        "dataserializers": {},
        "entity": {}
    },
    "items": {
        "item": {
            "coast_armor_trim_smithing_template": [
                null,
                {
                    "class": "cfs",
                    "field": "vT",
                    "max_stack_size": 64,
                    "numeric_id": 1189,
                    "text_id": "coast_armor_trim_smithing_template"
                }
            ],
            "dune_armor_trim_smithing_template": [
                null,
                {
                    "class": "cfs",
                    "field": "vS",
                    "max_stack_size": 64,
                    "numeric_id": 1188,
                    "text_id": "dune_armor_trim_smithing_template"
                }
            ],
            "eye_armor_trim_smithing_template": [
                null,
                {
                    "class": "cfs",
                    "field": "vW",
                    "max_stack_size": 64,
                    "numeric_id": 1192,
                    "text_id": "eye_armor_trim_smithing_template"
                }
            ],
            "netherite_upgrade_smithing_template": [
                null,
                {
                    "class": "cfs",
                    "field": "vQ",
                    "max_stack_size": 64,
                    "numeric_id": 1186,
                    "text_id": "netherite_upgrade_smithing_template"
                }
            ],
            "rib_armor_trim_smithing_template": [
                null,
                {
                    "class": "cfs",
                    "field": "wa",
                    "max_stack_size": 64,
                    "numeric_id": 1196,
                    "text_id": "rib_armor_trim_smithing_template"
                }
            ],
            "sentry_armor_trim_smithing_template": [
                null,
                {
                    "class": "cfs",
                    "field": "vR",
                    "max_stack_size": 64,
                    "numeric_id": 1187,
                    "text_id": "sentry_armor_trim_smithing_template"
                }
            ],
            "snout_armor_trim_smithing_template": [
                null,
                {
                    "class": "cfs",
                    "field": "vZ",
                    "max_stack_size": 64,
                    "numeric_id": 1195,
                    "text_id": "snout_armor_trim_smithing_template"
                }
            ],
            "spire_armor_trim_smithing_template": [
                null,
                {
                    "class": "cfs",
                    "field": "wb",
                    "max_stack_size": 64,
                    "numeric_id": 1197,
                    "text_id": "spire_armor_trim_smithing_template"
                }
            ],
            "tide_armor_trim_smithing_template": [
                null,
                {
                    "class": "cfs",
                    "field": "vY",
                    "max_stack_size": 64,
                    "numeric_id": 1194,
                    "text_id": "tide_armor_trim_smithing_template"
                }
            ],
            "vex_armor_trim_smithing_template": [
                null,
                {
                    "class": "cfs",
                    "field": "vX",
                    "max_stack_size": 64,
                    "numeric_id": 1193,
                    "text_id": "vex_armor_trim_smithing_template"
                }
            ],
            "ward_armor_trim_smithing_template": [
                null,
                {
                    "class": "cfs",
                    "field": "vV",
                    "max_stack_size": 64,
                    "numeric_id": 1191,
                    "text_id": "ward_armor_trim_smithing_template"
                }
            ],
            "wild_armor_trim_smithing_template": [
                null,
                {
                    "class": "cfs",
                    "field": "vU",
                    "max_stack_size": 64,
                    "numeric_id": 1190,
                    "text_id": "wild_armor_trim_smithing_template"
                }
            ]
        }
    },
    "language": {
        "container": {
            "upgrade.error_tooltip": [
                null,
                "Your item cannot be upgraded in this way"
            ],
            "upgrade.missing_template_tooltip": [
                null,
                "Put a Smithing Template here"
            ]
        },
        "item": {
            "minecraft.smithing_template": [
                null,
                "Smithing Template"
            ],
            "minecraft.smithing_template.applies_to": [
                null,
                "Applies to:"
            ],
            "minecraft.smithing_template.armor_trim.additions_slot_description": [
                null,
                "Put an ingot or crystal here"
            ],
            "minecraft.smithing_template.armor_trim.applies_to": [
                null,
                "Armor"
            ],
            "minecraft.smithing_template.armor_trim.base_slot_description": [
                null,
                "Put a piece of armor here"
            ],
            "minecraft.smithing_template.armor_trim.ingredients": [
                null,
                "Ingots & Crystals"
            ],
            "minecraft.smithing_template.ingredients": [
                null,
                "Ingredients:"
            ],
            "minecraft.smithing_template.netherite_upgrade.additions_slot_description": [
                null,
                "Put Netherite Ingot here"
            ],
            "minecraft.smithing_template.netherite_upgrade.applies_to": [
                null,
                "Diamond Equipment"
            ],
            "minecraft.smithing_template.netherite_upgrade.base_slot_description": [
                null,
                "Put a piece of Diamond armor, weapon or tool here"
            ],
            "minecraft.smithing_template.netherite_upgrade.ingredients": [
                null,
                "Netherite Ingot"
            ],
            "minecraft.smithing_template.upgrade": [
                null,
                "Upgrade: "
            ]
        },
        "selectWorld": {
            "mapFeatures.info": [
                "Villages, dungeons etc.",
                "Villages, Shipwrecks etc."
            ]
        },
        "trim_material": [
            null,
            {
                "minecraft.amethyst": "Amethyst Material",
                "minecraft.copper": "Copper Material",
                "minecraft.diamond": "Diamond Material",
                "minecraft.emerald": "Emerald Material",
                "minecraft.gold": "Gold Material",
                "minecraft.iron": "Iron Material",
                "minecraft.lapis": "Lapis Material",
                "minecraft.netherite": "Netherite Material",
                "minecraft.quartz": "Quartz Material",
                "minecraft.redstone": "Redstone Material"
            }
        ],
        "trim_pattern": [
            null,
            {
                "minecraft.coast": "Coast Armor Trim",
                "minecraft.dune": "Dune Armor Trim",
                "minecraft.eye": "Eye Armor Trim",
                "minecraft.rib": "Rib Armor Trim",
                "minecraft.sentry": "Sentry Armor Trim",
                "minecraft.snout": "Snout Armor Trim",
                "minecraft.spire": "Spire Armor Trim",
                "minecraft.tide": "Tide Armor Trim",
                "minecraft.vex": "Vex Armor Trim",
                "minecraft.ward": "Ward Armor Trim",
                "minecraft.wild": "Wild Armor Trim"
            }
        ],
        "upgrade": [
            null,
            {
                "minecraft.netherite_upgrade": "Netherite Upgrade"
            }
        ]
    },
    "packets": {
        "packet": {}
    },
    "pluginchannels": {},
    "recipes": {},
    "sounds": {},
    "stats": {},
    "tags": {},
    "tileentity": {
        "tileentities": {}
    },
    "version": {
        "data": [
            3320,
            3321
        ],
        "id": [
            "23w03a",
            "23w04a"
        ],
        "name": [
            "23w03a",
            "23w04a"
        ],
        "protocol": [
            1073741939,
            1073741940
        ]
    }
}